corpus/__init__.py
corpus/ccupdate.py
corpus/config.py
corpus/event.py
corpus/eventcorpus.py
corpus/eventrating.py
corpus/eventseriescompletion.py
corpus/eventtransfer.py
corpus/location.py
corpus/locationfixer.py
corpus/lookup.py
corpus/nominatim.py
corpus/version.py
corpus/datasources/__init__.py
corpus/datasources/acm.py
corpus/datasources/confref.py
corpus/datasources/crossref.py
corpus/datasources/dblp.py
corpus/datasources/dblpxml.py
corpus/datasources/drops.py
corpus/datasources/gnd.py
corpus/datasources/openresearch.py
corpus/datasources/tibkat.py
corpus/datasources/tibkatftx.py
corpus/datasources/webscrape.py
corpus/datasources/wikicfp.py
corpus/datasources/wikicfpscrape.py
corpus/datasources/wikidata.py
corpus/matching/__init__.py
corpus/matching/evaluation.py
corpus/quality/__init__.py
corpus/quality/painscale.py
corpus/quality/rating.py
corpus/utils/DatePolarHistogram.py
corpus/utils/__init__.py
corpus/utils/download.py
corpus/utils/figure.py
corpus/utils/isbn.py
corpus/utils/plots.py
corpus/utils/progress.py
corpus/utils/textparse.py
corpus/xmlhandler/__init__.py
corpus/xmlhandler/xmlparser.py
ptp/__init__.py
ptp/eventrefparser.py
ptp/ordinal.py
ptp/parsing.py
ptp/signature.py
resources/__init__.py
resources/acronyms.yaml
resources/cc.yaml
resources/cityNamePrefixes.yaml
resources/cityNames.yaml
resources/confref.yaml
resources/countries.yaml
resources/crossref.yaml
resources/dictionary.yaml
resources/endpoints.yaml
resources/formats.yaml
resources/gnd.yaml
resources/queries.yaml
resources/regions.yaml
resources/signature.yaml
resources/tibkat.yaml
resources/wikicfp.yaml
resources/wikidata.yaml
resources/years.yaml
resources/matching/training_set.json
ConferenceCorpus-0.1.1.dist-info/LICENSE
ConferenceCorpus-0.1.1.dist-info/METADATA
ConferenceCorpus-0.1.1.dist-info/WHEEL
ConferenceCorpus-0.1.1.dist-info/entry_points.txt
ConferenceCorpus-0.1.1.dist-info/top_level.txt
ConferenceCorpus-0.1.1.dist-info/RECORD
