Metadata-Version: 2.1
Name: ConferenceCorpus
Version: 0.1.1
Summary: python api providing access to academic events and event series from different sources
Home-page: http://wiki.bitplan.com/index.php/ConferenceCorpus
Download-URL: https://github.com/WolfgangFahl/ConferenceCorpus
Author: Wolfgang Fahl
Author-email: wf@bitplan.com
License: Apache
Project-URL: Code, https://github.com/WolfgangFahl/ConferenceCorpus
Project-URL: Issue tracker, https://github.com/WolfgangFahl/ConferenceCorpus/issues
Classifier: Programming Language :: Python
Classifier: Programming Language :: Python :: 3.8
Classifier: Programming Language :: Python :: 3.9
Classifier: Programming Language :: Python :: 3.10
License-File: LICENSE
Requires-Dist: pyFlaskBootstrap4 (>=0.5.1)
Requires-Dist: pylodstorage (>=0.4.7)
Requires-Dist: python-dateutil (>=2.8.2)
Requires-Dist: py-3rdparty-mediawiki (>=0.8.0)
Requires-Dist: wikirender (>=0.0.43)
Requires-Dist: geograpy3 (>=0.2.4)
Requires-Dist: habanero
Requires-Dist: geopy
Requires-Dist: OSMPythonTools (>=0.3.3)
Requires-Dist: wikibaseintegrator (>=0.12.1)
Requires-Dist: pybtex (>=0.24.0)
Requires-Dist: num2words (>=0.5.9)
Requires-Dist: psutil (>=5.9.0)
Requires-Dist: lxml (>=4.9.1)
Requires-Dist: pydevd (>=2.9.1)
Requires-Dist: pyGenericSpreadSheet
Requires-Dist: pyJustpyWidgets (>=0.1.11)
Requires-Dist: pyProbabilityDistributionFit (>=0.0.4)
Requires-Dist: matplotlib (>=3.6.0)
Requires-Dist: Markdown (>=3.3.7)
Requires-Dist: pyparsing (>=3.0.9)
Requires-Dist: scikit-learn (>=1.1.2)
Requires-Dist: requests (>=2.28.1)
